<?xml version="1.0" encoding="utf-8"?>
<EccTable>
    <!--
        Turkey
        The attribute definition for tag EccEntry:
        - Ecc: the emergnecy number
        - Category: the service category
        - Condition: there are following values:
            - 0: ecc only when no sim
            - 1: ecc always
            - 2: MMI will show ecc but send to nw as normal call
    -->
	<!--SR: modify for Ecc BEBXQLLE-152443 by zhouzihan 20220804 start -->
    <!--SR: add reason 142402 update emergency number to Excel-0530 by aidonghu  20220608 start-->
    <EccEntry Ecc="112" Category="0" Condition="2" />
    <EccEntry Ecc="133" Category="0" Condition="2" />
    <EccEntry Ecc="122" Category="0" Condition="2" />
    <EccEntry Ecc="144" Category="0" Condition="2" />
    <EccEntry Ecc="128" Category="0" Condition="2" />
    <EccEntry Ecc="911" Category="0" Condition="1" />
    <EccEntry Ecc="999" Category="0" Condition="1" />
    <EccEntry Ecc="140" Category="0" Condition="2" />
    <!--SR: add reason 142402 update emergency number to Excel-0530 by aidonghu  20220608 end-->
	<!--SR: modify for Ecc BEBXQLLE-152443 by zhouzihan 20220804 end -->
</EccTable>